impyrial/__init__.py
impyrial/utils.py
impyrial/length/__init__.py
impyrial/length/api.py
impyrial/length/core.py
impyrial/weight/__init__.py
impyrial/weight/api.py
impyrial/weight/core.py
impyrial-0.1.0.dist-info/METADATA
impyrial-0.1.0.dist-info/WHEEL
impyrial-0.1.0.dist-info/top_level.txt
impyrial-0.1.0.dist-info/RECORD
