Metadata-Version: 2.1
Name: impyrial
Version: 0.1.0
Summary: A package for converting imperial lengths and weights.
Home-page: UNKNOWN
Author: Januario Cipriano
License: UNKNOWN
Platform: UNKNOWN
Requires-Python: >=3.5
Requires-Dist: numpy (>=1.10)
Requires-Dist: pandas
